fdfgen/__init__.py
fdfgen-0.16.1.dist-info/DESCRIPTION.rst
fdfgen-0.16.1.dist-info/METADATA
fdfgen-0.16.1.dist-info/RECORD
fdfgen-0.16.1.dist-info/WHEEL
fdfgen-0.16.1.dist-info/metadata.json
fdfgen-0.16.1.dist-info/top_level.txt
